[ {
  "@id" : "http://www.wikidata.org/entity/Q478419",
  "http://example.com/abbreviated_title" : [ {
    "@value" : "J. Bacteriol."
  } ],
  "http://example.com/alternate_titles" : [ {
    "@language" : "en",
    "@value" : "J. bacteriol."
  } ],
  "http://example.com/bhl" : [ {
    "@value" : "8644"
  } ],
  "http://example.com/crossref" : [ {
    "@value" : "5544"
  } ],
  "http://example.com/dialnet" : [ {
    "@value" : "760"
  } ],
  "http://example.com/from_year" : [ {
    "@value" : "1916"
  } ],
  "http://example.com/homepage_url" : [ {
    "@id" : "http://www.journals.asm.org"
  }, {
    "@id" : "http://bibpurl.oclc.org/web/6701"
  }, {
    "@id" : "http://jb.asm.org/"
  } ],
  "http://example.com/issn_l" : [ {
    "@value" : "0021-9193"
  } ],
  "http://example.com/openalex" : [ {
    "@value" : "S133274750"
  }, {
    "@value" : "S4306556652"
  } ],
  "http://schema.org/issn" : [ {
    "@value" : "1067-8832"
  }, {
    "@value" : "1098-5530"
  }, {
    "@value" : "0021-9193"
  } ],
  "http://schema.org/name" : [ {
    "@language" : "en",
    "@value" : "Journal of Bacteriology"
  } ]
} ]