[ {
  "@id" : "http://www.wikidata.org/entity/Q5195034",
  "http://example.com/alternate_titles" : [ {
    "@language" : "es",
    "@value" : "CA"
  }, {
    "@language" : "es",
    "@value" : "Journal of Current Anthropology"
  } ],
  "http://example.com/crossref" : [ {
    "@value" : "4898"
  } ],
  "http://example.com/dialnet" : [ {
    "@value" : "3970"
  } ],
  "http://example.com/from_year" : [ {
    "@value" : "1959"
  } ],
  "http://example.com/homepage_url" : [ {
    "@id" : "http://www.journals.uchicago.edu/ca"
  }, {
    "@id" : "http://www.journals.uchicago.edu/CA/journal/"
  }, {
    "@id" : "http://www.journals.uchicago.edu/CA/journal/index.html"
  }, {
    "@id" : "http://www.jstor.org/journals/00113204.html"
  } ],
  "http://example.com/issn_l" : [ {
    "@value" : "0011-3204"
  } ],
  "http://example.com/jstor" : [ {
    "@value" : "curranth"
  } ],
  "http://example.com/openalex" : [ {
    "@value" : "S165709033"
  } ],
  "http://schema.org/issn" : [ {
    "@value" : "1537-5382"
  }, {
    "@value" : "0011-3204"
  } ],
  "http://schema.org/name" : [ {
    "@language" : "en",
    "@value" : "Current Anthropology"
  } ]
} ]