[ {
  "@id" : "http://www.wikidata.org/entity/Q119340990",
  "http://example.com/alternate_titles" : [ {
    "@language" : "en",
    "@value" : "Metaleptea: The Orthopterists' Newsletter"
  }, {
    "@language" : "en",
    "@value" : "Metalpeptea: The Newsletter of the Orthopterists’ Society"
  } ],
  "http://example.com/homepage_url" : [ {
    "@id" : "http://140.247.119.138/OrthSoc/metaleptea.htm"
  }, {
    "@id" : "http://140.247.119.225/OrthSoc/Metaleptea.html"
  }, {
    "@id" : "http://resolver.library.cornell.edu/misc/3935859"
  }, {
    "@id" : "https://orthsoc.org/publications/metaleptea/"
  } ],
  "http://example.com/issn_l" : [ {
    "@value" : "2372-2517"
  } ],
  "http://schema.org/issn" : [ {
    "@value" : "2372-2479"
  }, {
    "@value" : "2372-2517"
  } ],
  "http://schema.org/name" : [ {
    "@language" : "en",
    "@value" : "Metaleptea"
  }, {
    "@language" : "mul",
    "@value" : "Metaleptea"
  } ]
} ]